{
    "batch_year": 2023,
    "by_position": [
        {
            "position": "Director",
            "count": 16
        },
        {
            "position": "Deputy Secretary",
            "count": 8
        },
        {
            "position": "Joint Secretary",
            "count": 3
        }
    ],
    "entrants": [
        {
            "id": 63,
            "name": "Aashima Bhatnagar",
            "batch_year": 2023,
            "position": "Deputy Secretary",
            "department": "Health & Family Welfare",
            "ministry": "Ministry of Health & Family Welfare",
            "state": null,
            "photo_url": null,
            "profile_summary": null,
            "educational_background": null,
            "previous_experience": null,
            "date_of_appointment": null,
            "retirement_date": null,
            "created_at": "2025-11-25 07:12:14",
            "updated_at": "2025-11-25 07:12:14",
            "appointment_type": null,
            "extension_date": null,
            "current_status": "Active",
            "verified_source": "Lok Sabha Unstarred Question No. 3831 (18.12.2024) - Annexure-I"
        },
        {
            "id": 64,
            "name": "Ajay Kumar Arora",
            "batch_year": 2023,
            "position": "Joint Secretary",
            "department": "Legal Affairs",
            "ministry": "Ministry of Law and Justice",
            "state": null,
            "photo_url": null,
            "profile_summary": null,
            "educational_background": null,
            "previous_experience": null,
            "date_of_appointment": null,
            "retirement_date": null,
            "created_at": "2025-11-25 07:12:14",
            "updated_at": "2025-11-25 07:12:14",
            "appointment_type": null,
            "extension_date": null,
            "current_status": "Active",
            "verified_source": "Lok Sabha Unstarred Question No. 3831 (18.12.2024) - Annexure-I"
        },
        {
            "id": 65,
            "name": "G Sarathy Raja",
            "batch_year": 2023,
            "position": "Deputy Secretary",
            "department": "Steel",
            "ministry": "Ministry of Steel",
            "state": null,
            "photo_url": null,
            "profile_summary": null,
            "educational_background": null,
            "previous_experience": null,
            "date_of_appointment": null,
            "retirement_date": null,
            "created_at": "2025-11-25 07:12:14",
            "updated_at": "2025-11-25 07:12:14",
            "appointment_type": null,
            "extension_date": null,
            "current_status": "Active",
            "verified_source": "Lok Sabha Unstarred Question No. 3831 (18.12.2024) - Annexure-I"
        },
        {
            "id": 66,
            "name": "Hardik Sheth",
            "batch_year": 2023,
            "position": "Director",
            "department": "Financial Services",
            "ministry": "Department of Financial Services",
            "state": null,
            "photo_url": null,
            "profile_summary": null,
            "educational_background": null,
            "previous_experience": null,
            "date_of_appointment": null,
            "retirement_date": null,
            "created_at": "2025-11-25 07:12:14",
            "updated_at": "2025-11-25 07:12:14",
            "appointment_type": null,
            "extension_date": null,
            "current_status": "Active",
            "verified_source": "Lok Sabha Unstarred Question No. 3831 (18.12.2024) - Annexure-I"
        },
        {
            "id": 67,
            "name": "Harikumar Janakiraman",
            "batch_year": 2023,
            "position": "Director",
            "department": "School Education & Literacy",
            "ministry": "Ministry of Education",
            "state": null,
            "photo_url": null,
            "profile_summary": null,
            "educational_background": null,
            "previous_experience": null,
            "date_of_appointment": null,
            "retirement_date": null,
            "created_at": "2025-11-25 07:12:14",
            "updated_at": "2025-11-25 07:12:14",
            "appointment_type": null,
            "extension_date": null,
            "current_status": "Active",
            "verified_source": "Lok Sabha Unstarred Question No. 3831 (18.12.2024) - Annexure-I"
        },
        {
            "id": 68,
            "name": "Himanshu Joshi",
            "batch_year": 2023,
            "position": "Deputy Secretary",
            "department": "Statistics & Programme Implementation",
            "ministry": "Ministry of Statistics and Programme Implementation",
            "state": null,
            "photo_url": null,
            "profile_summary": null,
            "educational_background": null,
            "previous_experience": null,
            "date_of_appointment": null,
            "retirement_date": null,
            "created_at": "2025-11-25 07:12:14",
            "updated_at": "2025-11-25 07:12:14",
            "appointment_type": null,
            "extension_date": null,
            "current_status": "Active",
            "verified_source": "Lok Sabha Unstarred Question No. 3831 (18.12.2024) - Annexure-I"
        },
        {
            "id": 69,
            "name": "Hitendra Sahu",
            "batch_year": 2023,
            "position": "Director",
            "department": "Pharmaceuticals",
            "ministry": "Department of Pharmaceuticals",
            "state": null,
            "photo_url": null,
            "profile_summary": null,
            "educational_background": null,
            "previous_experience": null,
            "date_of_appointment": null,
            "retirement_date": null,
            "created_at": "2025-11-25 07:12:14",
            "updated_at": "2025-11-25 07:12:14",
            "appointment_type": null,
            "extension_date": null,
            "current_status": "Active",
            "verified_source": "Lok Sabha Unstarred Question No. 3831 (18.12.2024) - Annexure-I"
        },
        {
            "id": 70,
            "name": "Indranil Das",
            "batch_year": 2023,
            "position": "Director",
            "department": "Health and Family Welfare",
            "ministry": "Ministry of Health and Family Welfare",
            "state": null,
            "photo_url": null,
            "profile_summary": null,
            "educational_background": null,
            "previous_experience": null,
            "date_of_appointment": null,
            "retirement_date": null,
            "created_at": "2025-11-25 07:12:14",
            "updated_at": "2025-11-25 07:12:14",
            "appointment_type": null,
            "extension_date": null,
            "current_status": "Active",
            "verified_source": "Lok Sabha Unstarred Question No. 3831 (18.12.2024) - Annexure-I"
        },
        {
            "id": 71,
            "name": "Jigneshkumar Pareshbhai Solanki",
            "batch_year": 2023,
            "position": "Director",
            "department": "Financial Services",
            "ministry": "Department of Financial Services",
            "state": null,
            "photo_url": null,
            "profile_summary": null,
            "educational_background": null,
            "previous_experience": null,
            "date_of_appointment": null,
            "retirement_date": null,
            "created_at": "2025-11-25 07:12:14",
            "updated_at": "2025-11-25 07:12:14",
            "appointment_type": null,
            "extension_date": null,
            "current_status": "Active",
            "verified_source": "Lok Sabha Unstarred Question No. 3831 (18.12.2024) - Annexure-I"
        },
        {
            "id": 72,
            "name": "Madhu Sudana Sankar",
            "batch_year": 2023,
            "position": "Joint Secretary",
            "department": "Civil Aviation",
            "ministry": "Ministry of Civil Aviation",
            "state": null,
            "photo_url": null,
            "profile_summary": null,
            "educational_background": null,
            "previous_experience": null,
            "date_of_appointment": null,
            "retirement_date": null,
            "created_at": "2025-11-25 07:12:14",
            "updated_at": "2025-11-25 07:12:14",
            "appointment_type": null,
            "extension_date": null,
            "current_status": "Active",
            "verified_source": "Lok Sabha Unstarred Question No. 3831 (18.12.2024) - Annexure-I"
        },
        {
            "id": 73,
            "name": "Manish Kumar",
            "batch_year": 2023,
            "position": "Deputy Secretary",
            "department": "Heavy Industries",
            "ministry": "Ministry of Heavy Industries",
            "state": null,
            "photo_url": null,
            "profile_summary": null,
            "educational_background": null,
            "previous_experience": null,
            "date_of_appointment": null,
            "retirement_date": null,
            "created_at": "2025-11-25 07:12:14",
            "updated_at": "2025-11-25 07:12:14",
            "appointment_type": null,
            "extension_date": null,
            "current_status": "Active",
            "verified_source": "Lok Sabha Unstarred Question No. 3831 (18.12.2024) - Annexure-I"
        },
        {
            "id": 74,
            "name": "Manish Mishra",
            "batch_year": 2023,
            "position": "Director",
            "department": "Power",
            "ministry": "Ministry of Power",
            "state": null,
            "photo_url": null,
            "profile_summary": null,
            "educational_background": null,
            "previous_experience": null,
            "date_of_appointment": null,
            "retirement_date": null,
            "created_at": "2025-11-25 07:12:14",
            "updated_at": "2025-11-25 07:12:14",
            "appointment_type": null,
            "extension_date": null,
            "current_status": "Active",
            "verified_source": "Lok Sabha Unstarred Question No. 3831 (18.12.2024) - Annexure-I"
        },
        {
            "id": 75,
            "name": "Manoj Muttathil",
            "batch_year": 2023,
            "position": "Joint Secretary",
            "department": "Financial Services",
            "ministry": "Department of Financial Services",
            "state": null,
            "photo_url": null,
            "profile_summary": null,
            "educational_background": null,
            "previous_experience": null,
            "date_of_appointment": null,
            "retirement_date": null,
            "created_at": "2025-11-25 07:12:14",
            "updated_at": "2025-11-25 07:12:14",
            "appointment_type": null,
            "extension_date": null,
            "current_status": "Active",
            "verified_source": "Lok Sabha Unstarred Question No. 3831 (18.12.2024) - Annexure-I"
        },
        {
            "id": 76,
            "name": "Minal Soni",
            "batch_year": 2023,
            "position": "Deputy Secretary",
            "department": "Statistics & Programme Implementation",
            "ministry": "Ministry of Statistics and Programme Implementation",
            "state": null,
            "photo_url": null,
            "profile_summary": null,
            "educational_background": null,
            "previous_experience": null,
            "date_of_appointment": null,
            "retirement_date": null,
            "created_at": "2025-11-25 07:12:14",
            "updated_at": "2025-11-25 07:12:14",
            "appointment_type": null,
            "extension_date": null,
            "current_status": "Active",
            "verified_source": "Lok Sabha Unstarred Question No. 3831 (18.12.2024) - Annexure-I"
        },
        {
            "id": 77,
            "name": "Neeraj Prakash",
            "batch_year": 2023,
            "position": "Director",
            "department": "Statistics & Programme Implementation",
            "ministry": "Ministry of Statistics and Programme Implementation",
            "state": null,
            "photo_url": null,
            "profile_summary": null,
            "educational_background": null,
            "previous_experience": null,
            "date_of_appointment": null,
            "retirement_date": null,
            "created_at": "2025-11-25 07:12:14",
            "updated_at": "2025-11-25 07:12:14",
            "appointment_type": null,
            "extension_date": null,
            "current_status": "Active",
            "verified_source": "Lok Sabha Unstarred Question No. 3831 (18.12.2024) - Annexure-I"
        },
        {
            "id": 78,
            "name": "Priya Jacob",
            "batch_year": 2023,
            "position": "Director",
            "department": "Food and Public Distribution",
            "ministry": "Department of Food and Public Distribution",
            "state": null,
            "photo_url": null,
            "profile_summary": null,
            "educational_background": null,
            "previous_experience": null,
            "date_of_appointment": null,
            "retirement_date": null,
            "created_at": "2025-11-25 07:12:14",
            "updated_at": "2025-11-25 07:12:14",
            "appointment_type": null,
            "extension_date": null,
            "current_status": "Active",
            "verified_source": "Lok Sabha Unstarred Question No. 3831 (18.12.2024) - Annexure-I"
        },
        {
            "id": 79,
            "name": "Rajeshwari S Mallegowda",
            "batch_year": 2023,
            "position": "Director",
            "department": "Rural Development",
            "ministry": "Ministry of Rural Development",
            "state": null,
            "photo_url": null,
            "profile_summary": null,
            "educational_background": null,
            "previous_experience": null,
            "date_of_appointment": null,
            "retirement_date": null,
            "created_at": "2025-11-25 07:12:14",
            "updated_at": "2025-11-25 07:12:14",
            "appointment_type": null,
            "extension_date": null,
            "current_status": "Active",
            "verified_source": "Lok Sabha Unstarred Question No. 3831 (18.12.2024) - Annexure-I"
        },
        {
            "id": 80,
            "name": "Ravi Ranjan Singh",
            "batch_year": 2023,
            "position": "Director",
            "department": "Agriculture & Farmers Welfare",
            "ministry": "Ministry of Agriculture & Farmers Welfare",
            "state": null,
            "photo_url": null,
            "profile_summary": null,
            "educational_background": null,
            "previous_experience": null,
            "date_of_appointment": null,
            "retirement_date": null,
            "created_at": "2025-11-25 07:12:14",
            "updated_at": "2025-11-25 07:12:14",
            "appointment_type": null,
            "extension_date": null,
            "current_status": "Active",
            "verified_source": "Lok Sabha Unstarred Question No. 3831 (18.12.2024) - Annexure-I"
        },
        {
            "id": 81,
            "name": "Rohina Gupta",
            "batch_year": 2023,
            "position": "Director",
            "department": "Housing and Urban Affairs",
            "ministry": "Ministry of Housing and Urban Affairs",
            "state": null,
            "photo_url": null,
            "profile_summary": null,
            "educational_background": null,
            "previous_experience": null,
            "date_of_appointment": null,
            "retirement_date": null,
            "created_at": "2025-11-25 07:12:14",
            "updated_at": "2025-11-25 07:12:14",
            "appointment_type": null,
            "extension_date": null,
            "current_status": "Active",
            "verified_source": "Lok Sabha Unstarred Question No. 3831 (18.12.2024) - Annexure-I"
        },
        {
            "id": 82,
            "name": "Sanjeev Kumar",
            "batch_year": 2023,
            "position": "Deputy Secretary",
            "department": "Statistics & Programme Implementation",
            "ministry": "Ministry of Statistics and Programme Implementation",
            "state": null,
            "photo_url": null,
            "profile_summary": null,
            "educational_background": null,
            "previous_experience": null,
            "date_of_appointment": null,
            "retirement_date": null,
            "created_at": "2025-11-25 07:12:14",
            "updated_at": "2025-11-25 07:12:14",
            "appointment_type": null,
            "extension_date": null,
            "current_status": "Active",
            "verified_source": "Lok Sabha Unstarred Question No. 3831 (18.12.2024) - Annexure-I"
        },
        {
            "id": 83,
            "name": "Santosh WB",
            "batch_year": 2023,
            "position": "Director",
            "department": "Chemicals and Petrochemicals",
            "ministry": "Department of Chemicals and Petrochemicals",
            "state": null,
            "photo_url": null,
            "profile_summary": null,
            "educational_background": null,
            "previous_experience": null,
            "date_of_appointment": null,
            "retirement_date": null,
            "created_at": "2025-11-25 07:12:14",
            "updated_at": "2025-11-25 07:12:14",
            "appointment_type": null,
            "extension_date": null,
            "current_status": "Active",
            "verified_source": "Lok Sabha Unstarred Question No. 3831 (18.12.2024) - Annexure-I"
        },
        {
            "id": 84,
            "name": "Saumya Rajan",
            "batch_year": 2023,
            "position": "Deputy Secretary",
            "department": "Higher Education",
            "ministry": "Ministry of Education",
            "state": null,
            "photo_url": null,
            "profile_summary": null,
            "educational_background": null,
            "previous_experience": null,
            "date_of_appointment": null,
            "retirement_date": null,
            "created_at": "2025-11-25 07:12:14",
            "updated_at": "2025-11-25 07:12:14",
            "appointment_type": null,
            "extension_date": null,
            "current_status": "Active",
            "verified_source": "Lok Sabha Unstarred Question No. 3831 (18.12.2024) - Annexure-I"
        },
        {
            "id": 85,
            "name": "Sharad Kumar Dwivedi",
            "batch_year": 2023,
            "position": "Director",
            "department": "Agriculture & Farmers Welfare",
            "ministry": "Ministry of Agriculture & Farmers Welfare",
            "state": null,
            "photo_url": null,
            "profile_summary": null,
            "educational_background": null,
            "previous_experience": null,
            "date_of_appointment": null,
            "retirement_date": null,
            "created_at": "2025-11-25 07:12:14",
            "updated_at": "2025-11-25 07:12:14",
            "appointment_type": null,
            "extension_date": null,
            "current_status": "Active",
            "verified_source": "Lok Sabha Unstarred Question No. 3831 (18.12.2024) - Annexure-I"
        },
        {
            "id": 86,
            "name": "Shubhankit Srivastava",
            "batch_year": 2023,
            "position": "Deputy Secretary",
            "department": "Heavy Industries",
            "ministry": "Ministry of Heavy Industries",
            "state": null,
            "photo_url": null,
            "profile_summary": null,
            "educational_background": null,
            "previous_experience": null,
            "date_of_appointment": null,
            "retirement_date": null,
            "created_at": "2025-11-25 07:12:14",
            "updated_at": "2025-11-25 07:12:14",
            "appointment_type": null,
            "extension_date": null,
            "current_status": "Active",
            "verified_source": "Lok Sabha Unstarred Question No. 3831 (18.12.2024) - Annexure-I"
        },
        {
            "id": 87,
            "name": "Simrat Kaur",
            "batch_year": 2023,
            "position": "Director",
            "department": "Department for Promotion of Industry & Internal Trade",
            "ministry": "Ministry of Commerce and Industry",
            "state": null,
            "photo_url": null,
            "profile_summary": null,
            "educational_background": null,
            "previous_experience": null,
            "date_of_appointment": null,
            "retirement_date": null,
            "created_at": "2025-11-25 07:12:14",
            "updated_at": "2025-11-25 07:12:14",
            "appointment_type": null,
            "extension_date": null,
            "current_status": "Active",
            "verified_source": "Lok Sabha Unstarred Question No. 3831 (18.12.2024) - Annexure-I"
        },
        {
            "id": 88,
            "name": "Sunil Kumar Sharma",
            "batch_year": 2023,
            "position": "Director",
            "department": "Power",
            "ministry": "Ministry of Power",
            "state": null,
            "photo_url": null,
            "profile_summary": null,
            "educational_background": null,
            "previous_experience": null,
            "date_of_appointment": null,
            "retirement_date": null,
            "created_at": "2025-11-25 07:12:14",
            "updated_at": "2025-11-25 07:12:14",
            "appointment_type": null,
            "extension_date": null,
            "current_status": "Active",
            "verified_source": "Lok Sabha Unstarred Question No. 3831 (18.12.2024) - Annexure-I"
        },
        {
            "id": 89,
            "name": "Vishnu Mishra",
            "batch_year": 2023,
            "position": "Director",
            "department": "Statistics & Programme Implementation",
            "ministry": "Ministry of Statistics and Programme Implementation",
            "state": null,
            "photo_url": null,
            "profile_summary": null,
            "educational_background": null,
            "previous_experience": null,
            "date_of_appointment": null,
            "retirement_date": null,
            "created_at": "2025-11-25 07:12:14",
            "updated_at": "2025-11-25 07:12:14",
            "appointment_type": null,
            "extension_date": null,
            "current_status": "Active",
            "verified_source": "Lok Sabha Unstarred Question No. 3831 (18.12.2024) - Annexure-I"
        }
    ]
}